hostp2pd/__init__.py
hostp2pd/__main__.py
hostp2pd/__version__.py
hostp2pd/hostp2pd.py
hostp2pd/hostp2pd.yaml
hostp2pd/interpreter.py
hostp2pd/pin.py
hostp2pd-0.1.7.dist-info/LICENSE
hostp2pd-0.1.7.dist-info/METADATA
hostp2pd-0.1.7.dist-info/WHEEL
hostp2pd-0.1.7.dist-info/entry_points.txt
hostp2pd-0.1.7.dist-info/top_level.txt
hostp2pd-0.1.7.dist-info/RECORD
