Metadata-Version: 2.1
Name: hostp2pd
Version: 0.1.7
Summary: Wi-Fi Direct Session Manager, implementing a host AP daemon in Wi-Fi Direct mode, including P2P WPS enrollment
Home-page: https://github.com/Ircama/hostp2pd
Author: Ircama
License: CC-BY-NC-SA-4.0
Keywords: wi-fi-direct p2p wpa-supplicant wpa-cli
Platform: UNKNOWN
Classifier: Operating System :: POSIX :: Linux
Classifier: License :: Other/Proprietary License
Classifier: Topic :: Communications
Classifier: Topic :: Software Development :: Libraries :: Python Modules
Classifier: Programming Language :: Python :: 3 :: Only
Classifier: Development Status :: 5 - Production/Stable
Classifier: Intended Audience :: System Administrators
Classifier: Intended Audience :: Telecommunications Industry
Classifier: Intended Audience :: Developers
Requires-Python: >3.5
Requires-Dist: python-daemon
Requires-Dist: pyyaml
